resemble_enhance/__init__.py
resemble_enhance/common.py
resemble_enhance/hparams.py
resemble_enhance/inference.py
resemble_enhance/melspec.py
resemble_enhance/version.py
resemble_enhance/data/__init__.py
resemble_enhance/data/dataset.py
resemble_enhance/data/utils.py
resemble_enhance/data/distorter/__init__.py
resemble_enhance/data/distorter/base.py
resemble_enhance/data/distorter/custom.py
resemble_enhance/data/distorter/distorter.py
resemble_enhance/data/distorter/sox.py
resemble_enhance/denoiser/__init__.py
resemble_enhance/denoiser/__main__.py
resemble_enhance/denoiser/denoiser.py
resemble_enhance/denoiser/hparams.py
resemble_enhance/denoiser/inference.py
resemble_enhance/denoiser/train.py
resemble_enhance/denoiser/unet.py
resemble_enhance/enhancer/__init__.py
resemble_enhance/enhancer/__main__.py
resemble_enhance/enhancer/download.py
resemble_enhance/enhancer/enhancer.py
resemble_enhance/enhancer/hparams.py
resemble_enhance/enhancer/inference.py
resemble_enhance/enhancer/train.py
resemble_enhance/enhancer/lcfm/__init__.py
resemble_enhance/enhancer/lcfm/cfm.py
resemble_enhance/enhancer/lcfm/irmae.py
resemble_enhance/enhancer/lcfm/lcfm.py
resemble_enhance/enhancer/lcfm/wn.py
resemble_enhance/enhancer/univnet/__init__.py
resemble_enhance/enhancer/univnet/amp.py
resemble_enhance/enhancer/univnet/discriminator.py
resemble_enhance/enhancer/univnet/lvcnet.py
resemble_enhance/enhancer/univnet/mrstft.py
resemble_enhance/enhancer/univnet/univnet.py
resemble_enhance/enhancer/univnet/alias_free_torch/__init__.py
resemble_enhance/enhancer/univnet/alias_free_torch/filter.py
resemble_enhance/enhancer/univnet/alias_free_torch/resample.py
resemble_enhance/utils/__init__.py
resemble_enhance/utils/control.py
resemble_enhance/utils/distributed.py
resemble_enhance/utils/engine.py
resemble_enhance/utils/logging.py
resemble_enhance/utils/train_loop.py
resemble_enhance/utils/utils.py
resemble_enhance-0.0.1.dist-info/LICENSE
resemble_enhance-0.0.1.dist-info/METADATA
resemble_enhance-0.0.1.dist-info/WHEEL
resemble_enhance-0.0.1.dist-info/entry_points.txt
resemble_enhance-0.0.1.dist-info/top_level.txt
resemble_enhance-0.0.1.dist-info/RECORD
