Metadata-Version: 2.1
Name: resemble-enhance
Version: 0.0.1
Summary: Speech denoising and enhancement with deep learning
Home-page: https://github.com/resemble-ai/resemble-enhance
Author: Resemble AI
Author-email: team@resemble.ai
Requires-Python: >=3.10
License-File: LICENSE
Requires-Dist: celluloid ==0.2.0
Requires-Dist: deepspeed ==0.12.4
Requires-Dist: librosa ==0.10.1
Requires-Dist: matplotlib ==3.8.1
Requires-Dist: numpy ==1.26.2
Requires-Dist: omegaconf ==2.3.0
Requires-Dist: pandas ==2.1.3
Requires-Dist: ptflops ==0.7.1.2
Requires-Dist: rich ==13.7.0
Requires-Dist: scipy ==1.11.4
Requires-Dist: soundfile ==0.12.1
Requires-Dist: torch ==2.1.1
Requires-Dist: torchaudio ==2.1.1
Requires-Dist: torchvision ==0.16.1
Requires-Dist: tqdm ==4.66.1
Requires-Dist: resampy ==0.4.2
Requires-Dist: tabulate ==0.8.10
Requires-Dist: gradio ==4.8.0
